byron/__python__.py
byron-0.0.dist-info/METADATA
byron-0.0.dist-info/WHEEL
byron-0.0.dist-info/RECORD
